bibtheque/__init__.py
bibtheque/bibtex.py
bibtheque/cache.py
bibtheque/cli.py
bibtheque/config.py
bibtheque/database.py
bibtheque/document.py
bibtheque/doi.py
bibtheque/fields.py
bibtheque/index.py
bibtheque/isbn.py
bibtheque/strings.py
bibtheque-0.1.20.dist-info/METADATA
bibtheque-0.1.20.dist-info/WHEEL
bibtheque-0.1.20.dist-info/entry_points.txt
bibtheque-0.1.20.dist-info/top_level.txt
bibtheque-0.1.20.dist-info/RECORD
