Metadata-Version: 2.2
Name: bibtheque
Version: 0.1.20
Summary: Bibliography management tool.
Author-email: Douglas Keller <dg.kllr.jr@gmail.com>
Project-URL: Homepage, https://github.com/BibTheque/PyBibtheque
Project-URL: Repository, https://github.com/BibTheque/PyBibtheque.git
Requires-Dist: click
Requires-Dist: pypdf
Requires-Dist: bibtexparser
Requires-Dist: isbnlib
Requires-Dist: habanero==2.0.0
Requires-Dist: numpy
Requires-Dist: numba
Requires-Dist: toml
